{
    "required": true,
    "package": "org.auioc.mcmod.hulsealib.mixin",
    "compatibilityLevel": "JAVA_17",
    "mixins": [
        "common.MixinCreativeModeTab",
        "common.MixinFoodData",
        "common.MixinItemStack",
        "common.MixinPistonBaseBlock",
        "server.MixinServerPlayer",
        "server.MixinLivingEntity",
        "server.MixinCatRelaxOnOwnerGoal",
        "server.MixinPiglinAi",
        "server.MixinEyeOfEnder",
        "server.MixinEnderEyeItem"
    ],
    "client": [],
    "server": [],
    "injectors": {
        "defaultRequire": 1
    },
    "refmap": "hulsealib.mixin-refmap.json",
    "minVersion": "0.8"
}
